<?xml version="1.0" encoding="UTF-8"?>
<root>
    <row>
        <manufacturer><![CDATA[Zonda Lighting]]></manufacturer>
        <name_of_store><![CDATA[Gaismas Market]]></name_of_store>
        <sku><![CDATA[SK-2845-600 G]]></sku>
        <name><![CDATA[Lustra SK-2845-600 G]]></name>
        <url_to_product><![CDATA[https://gaismasmarket.lv/lv/iekstelpu-apgaismojums/lustras/lustraslustra-sk-2845-600-glampy]]></url_to_product>
        <categories><![CDATA[Default Category/Interior & decors/Decor/Lamps & Lighting]]></categories><short_description><![CDATA[Lustra SK-2845-600 G]]></short_description>
        <color></color>
        <price>386.00</price>
        <special_price>250.90</special_price>
        <special_price_from_date></special_price_from_date>
        <special_price_to_date></special_price_to_date>
        <base_image><![CDATA[https://gaismasmarket.lv/image/cache/catalog/andris/dazads/zonda-2019/sk-2845-600-g-800x800.jpg]]></base_image>
        <small_image><![CDATA[https://gaismasmarket.lv/image/cache/catalog/andris/dazads/zonda-2019/sk-2845-600-g-800x800.jpg]]></small_image>
        <thumbnail_image><![CDATA[https://gaismasmarket.lv/image/cache/catalog/andris/dazads/zonda-2019/sk-2845-600-g-800x800.jpg]]></thumbnail_image>
    </row>
</root>
